mctools/__init__.py
mctools/test.py
zmctools-0.0.1.dist-info/LICENSE
zmctools-0.0.1.dist-info/METADATA
zmctools-0.0.1.dist-info/WHEEL
zmctools-0.0.1.dist-info/top_level.txt
zmctools-0.0.1.dist-info/RECORD
