Metadata-Version: 2.1
Name: zmctools
Version: 0.0.1
Summary: tools
Home-page: https://github.com/pypa/sampleproject
Author: zhongmc
Author-email: 1406433511@qq.com
Project-URL: Bug Tracker, https://github.com/pypa/sampleproject/issues
Classifier: Programming Language :: Python :: 3
Classifier: License :: OSI Approved :: MIT License
Classifier: Operating System :: OS Independent
Requires-Python: >=3.6
License-File: LICENSE
Requires-Dist: requests (==2.27.1)
Requires-Dist: pandas
